pdfcmd/__init__.py
pdfcmd/__main__.py
pdfcmd/pdfcmd.py
pdfcmd/commands/cat.py
pdfcmd/commands/help.py
pdfcmd/commands/info.py
pdfcmd/commands/pages.py
pdfcmd-1.13.dist-info/METADATA
pdfcmd-1.13.dist-info/WHEEL
pdfcmd-1.13.dist-info/entry_points.txt
pdfcmd-1.13.dist-info/top_level.txt
pdfcmd-1.13.dist-info/RECORD
