Metadata-Version: 2.4
Name: pdfcmd
Version: 1.13
Summary: Utility to perform commands on PDF files
Author-email: Mark Blakeney <mark.blakeney@bullet-systems.net>
License-Expression: GPL-3.0-or-later
Project-URL: Homepage, https://github.com/bulletmark/pdfcmd
Keywords: PDF,pypdf
Classifier: Programming Language :: Python :: 3
Requires-Python: >=3.8
Requires-Dist: argcomplete
Requires-Dist: pypdf>=3.1.0
